hanazeder/Hanazeder.py
hanazeder/__init__.py
hanazeder/comm.py
hanazeder/encoding.py
hanazeder/read.py
hanazeder/types.py
hanazeder-1.1.1.dist-info/LICENSE.txt
hanazeder-1.1.1.dist-info/METADATA
hanazeder-1.1.1.dist-info/WHEEL
hanazeder-1.1.1.dist-info/entry_points.txt
hanazeder-1.1.1.dist-info/top_level.txt
hanazeder-1.1.1.dist-info/RECORD
