Metadata-Version: 2.1
Name: hanazeder
Version: 1.1.1
Summary: Library and utils to read sensor data from Hanazeder FP heating pumps
Author-email: Kevin Read <me@kevin-read.com>
License: 
Project-URL: Homepage, https://github.com/unverbraucht/serial_hanazeder
Keywords: heating,smart home,hanazeder,pump
Classifier: License :: OSI Approved :: Apache Software License
Classifier: Programming Language :: Python
Classifier: Programming Language :: Python :: 3
Classifier: Development Status :: 4 - Beta
Classifier: Environment :: Console
Requires-Python: >=3.6
License-File: LICENSE.txt
Requires-Dist: crccheck
Requires-Dist: pyserial
Provides-Extra: dev
Requires-Dist: pytest ; extra == 'dev'
Requires-Dist: bumpver ; extra == 'dev'
Requires-Dist: build ; extra == 'dev'
Requires-Dist: twine ; extra == 'dev'
Requires-Dist: pytest-mock ; extra == 'dev'
